{
    "id": "7ee3067e-f75c-4cf5-a4c0-cea3fe67a5e6",
    "createTime": 1601117151230218,
    "modifiedTime": 1601355214827609,
    "author": "",
    "postScript": "",
    "name": "抖音歌曲",
    "host": "http://www.douyingequ.com",
    "group": "",
    "contentType": 3,
    "sort": 0,
    "useCryptoJS": false,
    "loadJs": "",
    "userAgent": "",
    "enableDiscover": true,
    "discoverUrl": "$host",
    "discoverItems": "",
    "discoverList": ".navList li",
    "discoverTags": "",
    "discoverName": "a@text",
    "discoverCover": "@js:\"https://ss1.bdstatic.com/70cFuXSh_Q1YnxGkpoWK1HF6hhy/it/u=3797573884,3491056961&fm=26&gp=0.jpg\"",
    "discoverAuthor": "",
    "discoverChapter": "span@text",
    "discoverDescription": "",
    "discoverResult": "a@href",
    "enableSearch": false,
    "searchUrl": "",
    "searchItems": "",
    "searchList": "",
    "searchTags": "",
    "searchName": "",
    "searchCover": "",
    "searchAuthor": "",
    "searchChapter": "",
    "searchDescription": "",
    "searchResult": "",
    "enableMultiRoads": false,
    "chapterRoads": "",
    "chapterRoadName": "",
    "chapterUrl": "",
    "chapterItems": "",
    "chapterList": ".songList li",
    "chapterName": ".songNum@text&&\n.songName@text",
    "chapterCover": "",
    "chapterLock": "",
    "chapterTime": "",
    "chapterResult": "a@href@js:\"http://www.douyingequ.com/json/\"+result.match(/[1-9]\\d*/)+\".json\"",
    "contentUrl": "",
    "contentItems": "@js:\nvar _txt=result.substr(1,result.length-2);\nvar _data=JSON.parse(_txt);\nresult=\"http://www.douyingequ.com/douyin/a\"+_data.id+\".htm\";\n@http:\n@css:#lrc_content@text@js:[_data.wma,\"@lrc\"+result];",
    "loginUrl": "",
    "cookies": "",
    "viewStyle": 0
}